{"slug":"cn/198","title":"如何是好 - 阎真","child":[{"slug":"cn/198/1","title":"1"},{"slug":"cn/198/2","title":"2"},{"slug":"cn/198/3","title":"3"},{"slug":"cn/198/4","title":"4"},{"slug":"cn/198/5","title":"5"},{"slug":"cn/198/6","title":"6"},{"slug":"cn/198/7","title":"7"},{"slug":"cn/198/8","title":"8"},{"slug":"cn/198/9","title":"9"},{"slug":"cn/198/10","title":"10"},{"slug":"cn/198/11","title":"11"},{"slug":"cn/198/12","title":"12"},{"slug":"cn/198/13","title":"13"},{"slug":"cn/198/14","title":"14"},{"slug":"cn/198/15","title":"15"},{"slug":"cn/198/16","title":"16"},{"slug":"cn/198/17","title":"17"},{"slug":"cn/198/18","title":"18"},{"slug":"cn/198/19","title":"19"},{"slug":"cn/198/20","title":"20"},{"slug":"cn/198/21","title":"21"},{"slug":"cn/198/22","title":"22"},{"slug":"cn/198/23","title":"23"},{"slug":"cn/198/24","title":"24"},{"slug":"cn/198/25","title":"25"},{"slug":"cn/198/26","title":"26"},{"slug":"cn/198/27","title":"27"},{"slug":"cn/198/28","title":"28"},{"slug":"cn/198/29","title":"29"},{"slug":"cn/198/30","title":"30"},{"slug":"cn/198/31","title":"31"},{"slug":"cn/198/32","title":"32"},{"slug":"cn/198/33","title":"33"},{"slug":"cn/198/34","title":"34"},{"slug":"cn/198/35","title":"35"},{"slug":"cn/198/36","title":"36"},{"slug":"cn/198/37","title":"37"},{"slug":"cn/198/38","title":"38"},{"slug":"cn/198/39","title":"39"},{"slug":"cn/198/40","title":"40"},{"slug":"cn/198/41","title":"41"},{"slug":"cn/198/42","title":"42"},{"slug":"cn/198/43","title":"43"},{"slug":"cn/198/44","title":"44"},{"slug":"cn/198/45","title":"45"},{"slug":"cn/198/46","title":"46"},{"slug":"cn/198/47","title":"47"},{"slug":"cn/198/48","title":"48"},{"slug":"cn/198/49","title":"49"},{"slug":"cn/198/50","title":"50"},{"slug":"cn/198/51","title":"51"},{"slug":"cn/198/52","title":"52"},{"slug":"cn/198/53","title":"53"},{"slug":"cn/198/54","title":"54"},{"slug":"cn/198/55","title":"55"},{"slug":"cn/198/56","title":"56"},{"slug":"cn/198/57","title":"57"},{"slug":"cn/198/58","title":"58"},{"slug":"cn/198/59","title":"59"},{"slug":"cn/198/60","title":"60"},{"slug":"cn/198/61","title":"61"},{"slug":"cn/198/62","title":"62"},{"slug":"cn/198/63","title":"63"},{"slug":"cn/198/64","title":"64"},{"slug":"cn/198/65","title":"65"},{"slug":"cn/198/66","title":"66"},{"slug":"cn/198/67","title":"67"},{"slug":"cn/198/68","title":"68"},{"slug":"cn/198/69","title":"69"},{"slug":"cn/198/70","title":"70"},{"slug":"cn/198/71","title":"71"},{"slug":"cn/198/72","title":"72"},{"slug":"cn/198/73","title":"73"},{"slug":"cn/198/74","title":"74"},{"slug":"cn/198/75","title":"75"},{"slug":"cn/198/76","title":"76"},{"slug":"cn/198/77","title":"77"},{"slug":"cn/198/78","title":"78"},{"slug":"cn/198/79","title":"79"},{"slug":"cn/198/80","title":"80"},{"slug":"cn/198/81","title":"81"},{"slug":"cn/198/82","title":"82"},{"slug":"cn/198/83","title":"83"},{"slug":"cn/198/84","title":"84"},{"slug":"cn/198/85","title":"85"},{"slug":"cn/198/86","title":"86"},{"slug":"cn/198/87","title":"87"}]}