{"slug":"cn/423","title":"在历史巨人身边：师哲回忆录 - 李海文","child":[{"slug":"cn/423/1","title":"在苏联留学"},{"slug":"cn/423/2","title":"投笔从戎"},{"slug":"cn/423/3","title":"到苏联去"},{"slug":"cn/423/4","title":"难以忘怀的基辅"},{"slug":"cn/423/5","title":"莫斯科军事工程兵学校（初级）"},{"slug":"cn/423/6","title":"在西伯利亚格贝乌工作的九年"},{"slug":"cn/423/7","title":"初进西伯利亚格贝乌工作"},{"slug":"cn/423/8","title":"第一次回国未成"},{"slug":"cn/423/9","title":"接待过境的我国抗日武装人员"},{"slug":"cn/423/10","title":"安置抗日将军马占山"},{"slug":"cn/423/11","title":"关于杨明斋的点滴情况"},{"slug":"cn/423/12","title":"我所知道的苏联1930年代的肃反"},{"slug":"cn/423/13","title":"被迫离开西伯利亚"},{"slug":"cn/423/14","title":"中共驻共产国际代表团"},{"slug":"cn/423/15","title":"初见团长任弼时"},{"slug":"cn/423/16","title":"莫尼诺——国际第二儿童院"},{"slug":"cn/423/17","title":"共产国际与中国共产党的关系"},{"slug":"cn/423/18","title":"中共代表团团长任弼时"},{"slug":"cn/423/19","title":"周恩来在共产国际"},{"slug":"cn/423/20","title":"随周恩来、任弼时一道回国"},{"slug":"cn/423/21","title":"初到延安"},{"slug":"cn/423/22","title":"第一次会见毛主席"},{"slug":"cn/423/23","title":"“骆驼”与“毛驴”"},{"slug":"cn/423/24","title":"任弼时担任中共中央秘书长"},{"slug":"cn/423/25","title":"中央书记张闻天"},{"slug":"cn/423/26","title":"敬爱的朱德总司令"},{"slug":"cn/423/27","title":"延安时期中共与共产国际、苏共之间的往来"},{"slug":"cn/423/28","title":"和毛泽东的一次谈话"},{"slug":"cn/423/29","title":"同共产国际（即远方）的关系"},{"slug":"cn/423/30","title":"毛泽东和斯大林的电报往来毛泽东给孙平讲课"},{"slug":"cn/423/31","title":"毛泽东的神韵"},{"slug":"cn/423/32","title":"主席和他的战友们"},{"slug":"cn/423/33","title":"主席深入群众，调查研究"},{"slug":"cn/423/34","title":"主席炯炯的目光"},{"slug":"cn/423/35","title":"主席的婚事"},{"slug":"cn/423/36","title":"整风运动和七大"},{"slug":"cn/423/37","title":"整风运动的顺利进行"},{"slug":"cn/423/38","title":"康生任总学委会副组长"},{"slug":"cn/423/39","title":"康生与“审干”、“抢救运动”"},{"slug":"cn/423/40","title":"处理绥德、关中“特务案”"},{"slug":"cn/423/41","title":"毛主席主持甄别工作"},{"slug":"cn/423/42","title":"第七次代表大会的召开"},{"slug":"cn/423/43","title":"记三位元帅"},{"slug":"cn/423/44","title":"八路军副总司令、军委副主席彭德怀"},{"slug":"cn/423/45","title":"陕甘宁晋绥联防军司令员贺龙"},{"slug":"cn/423/46","title":"徐向前二三事"},{"slug":"cn/423/47","title":"重庆谈判的前前后后"},{"slug":"cn/423/48","title":"抗日战争胜利 全面收复失地"},{"slug":"cn/423/49","title":"毛主席飞赴重庆"},{"slug":"cn/423/50","title":"苏军代表飞抵延安"},{"slug":"cn/423/51","title":"重庆谈判之后"},{"slug":"cn/423/52","title":"毛主席生病 斯大林派医生和毛岸英赴延安"},{"slug":"cn/423/53","title":"毛主席在卧室接见阿洛夫"},{"slug":"cn/423/54","title":"刘少奇主持中央工作时期"},{"slug":"cn/423/55","title":"在延安主持中央工作"},{"slug":"cn/423/56","title":"关于党的建设"},{"slug":"cn/423/57","title":"领导土地改革"},{"slug":"cn/423/58","title":"为击退国民党的进攻做好准备"},{"slug":"cn/423/59","title":"转战陕北"},{"slug":"cn/423/60","title":"主动撤离延安"},{"slug":"cn/423/61","title":"山西三交镇"},{"slug":"cn/423/62","title":"毛主席从枣林沟到朱官寨"},{"slug":"cn/423/63","title":"毛主席在神泉堡给斯大林写信"},{"slug":"cn/423/64","title":"能不能胜利 敢不敢胜利"},{"slug":"cn/423/65","title":"以革命的人道主义精神瓦解敌军"},{"slug":"cn/423/66","title":"发动土改"},{"slug":"cn/423/67","title":"从陕北经西柏坡到北平"},{"slug":"cn/423/68","title":"从容东进"},{"slug":"cn/423/69","title":"战略决战"},{"slug":"cn/423/70","title":"斯大林的特使米高扬来访"},{"slug":"cn/423/71","title":"中央进入北平 毛主席接见柯瓦廖夫"},{"slug":"cn/423/72","title":"建国前夕刘少奇访苏"},{"slug":"cn/423/73","title":"漫长的飞行"},{"slug":"cn/423/74","title":"刘少奇和斯大林会谈"},{"slug":"cn/423/75","title":"江青敬酒，刘少奇谦让，斯大林做自我批评"},{"slug":"cn/423/76","title":"斯大林与刘少奇依依惜别"},{"slug":"cn/423/77","title":"刘少奇在莫斯科参观、座谈"},{"slug":"cn/423/78","title":"刘少奇与苏联专家"},{"slug":"cn/423/79","title":"毛主席接见苏联文化艺术科学工作者代表团"},{"slug":"cn/423/80","title":"毛主席首次访苏"},{"slug":"cn/423/81","title":"行程万里"},{"slug":"cn/423/82","title":"两个伟人的首次会面"},{"slug":"cn/423/83","title":"斯大林让步了"},{"slug":"cn/423/84","title":"毛主席游览列宁格勒"},{"slug":"cn/423/85","title":"关于《中苏友好同盟互助条约》的谈判"},{"slug":"cn/423/86","title":"又一次误会"},{"slug":"cn/423/87","title":"签约 斯大林举行招待会"},{"slug":"cn/423/88","title":"斯大林破例出席告别宴会招待会"},{"slug":"cn/423/89","title":"登上归程"},{"slug":"cn/423/90","title":"尤金受邀来华"},{"slug":"cn/423/91","title":"尤金首次来华《实践论》的发表"},{"slug":"cn/423/92","title":"尤金第二次来华"},{"slug":"cn/423/93","title":"尤金担任驻华大使"},{"slug":"cn/423/94","title":"朝鲜战争期间的中苏关系"},{"slug":"cn/423/95","title":"朝鲜战争的开始与逆转"},{"slug":"cn/423/96","title":"周总理和斯大林会谈"},{"slug":"cn/423/97","title":"中国决定出兵援助朝鲜"},{"slug":"cn/423/98","title":"斯大林对苏联顾问与我方争论的态度"},{"slug":"cn/423/99","title":"朝中苏决定停战，进行和平谈判"},{"slug":"cn/423/100","title":"周总理、彭德怀和斯大林会谈"},{"slug":"cn/423/101","title":"1952年周恩来、刘少奇莫斯科之行"},{"slug":"cn/423/102","title":"周总理组织安排制订第一个五年计划"},{"slug":"cn/423/103","title":"周总理同斯大林及苏联政府代表团分别会谈"},{"slug":"cn/423/104","title":"周总理参观斯大林格勒及列宁运河"},{"slug":"cn/423/105","title":"刘少奇率中共代表团出席苏共十九大会见斯大林"},{"slug":"cn/423/106","title":"贝利亚被处决"},{"slug":"cn/423/107","title":"周总理率团出席日内瓦会议"},{"slug":"cn/423/108","title":"周总理对苏联的工作访问"},{"slug":"cn/423/109","title":"代表团飞抵日内瓦"},{"slug":"cn/423/110","title":"周恩来的机敏与智慧"},{"slug":"cn/423/111","title":"周恩来的才略与印度支那三国问题的解决"},{"slug":"cn/423/112","title":"周恩来和莫洛托夫互相合作"},{"slug":"cn/423/113","title":"周总理对日内瓦会议的总结"},{"slug":"cn/423/114","title":"赫鲁晓夫率团来华祝贺我国国庆五周年"},{"slug":"cn/423/115","title":"赫鲁晓夫上台"},{"slug":"cn/423/116","title":"毛泽东和赫鲁晓夫的会谈"},{"slug":"cn/423/117","title":"苏联代表团和我党领导人的交往"},{"slug":"cn/423/118","title":"苏联代表团在外地参观游览"},{"slug":"cn/423/119","title":"朱德出访东欧六国、参加苏共二十大"},{"slug":"cn/423/120","title":"参加罗马尼亚共产党第二次代表大会"},{"slug":"cn/423/121","title":"祝贺皮克总统八十寿辰"},{"slug":"cn/423/122","title":"访问匈牙利、捷克、波兰"},{"slug":"cn/423/123","title":"苏共二十大和我党《关于无产阶级专政的历史经验》的发表"},{"slug":"cn/423/124","title":"翻译的技巧和灵活性"},{"slug":"cn/423/125","title":"中国共产党第八次全国代表大会的召开"},{"slug":"cn/423/126","title":"米高扬向大会致贺词周恩来的谈话"},{"slug":"cn/423/127","title":"毛泽东一吐积郁"},{"slug":"cn/423/128","title":"波匈事件与刘少奇访苏"},{"slug":"cn/423/129","title":"苏联紧急通知"},{"slug":"cn/423/130","title":"赫鲁晓夫只身一人迎接"},{"slug":"cn/423/131","title":"刘少奇向苏共主席团慷慨进言"},{"slug":"cn/423/132","title":"宣言的产生"},{"slug":"cn/423/133","title":"提出对匈牙利事件的处理方案"},{"slug":"cn/423/134","title":"离开毛泽东身边"},{"slug":"cn/423/135","title":"索引"},{"slug":"cn/423/136","title":"部分中外人名、地名对照表"},{"slug":"cn/423/137","title":"大事记（1900—1957）"}]}