{
  "slug": "cn/216",
  "title": "上学记 - 何兆武、文靖",
  "child": [
    {
      "slug": "cn/216/0",
      "title": "序 那一代中国知识分子的幸福和自由",
      "child": [
        { "slug": "cn/216/0/1", "title": "一、亲历历史：那一代的人和事" },
        {
          "slug": "cn/216/0/2",
          "title": "二、幸福：什么是那一代中国知识分子的追求？"
        },
        { "slug": "cn/216/0/3", "title": "三、教养：值得讨论的话题" },
        { "slug": "cn/216/0/4", "title": "结语" }
      ]
    },
    {
      "slug": "cn/216/1",
      "title": "第一章（1921—1939）",
      "child": [
        { "slug": "cn/216/1/1", "title": "我的祖上没有名人" },
        { "slug": "cn/216/1/2", "title": "三民主义的少年兵" },
        { "slug": "cn/216/1/3", "title": "“一二·九”见闻" },
        {
          "slug": "cn/216/1/4",
          "title": "上学记·甲",
          "child": [
            { "slug": "cn/216/1/4/1", "title": "1. 力矫时弊，以古为则？" },
            { "slug": "cn/216/1/4/2", "title": "2. 无故乱翻书" },
            { "slug": "cn/216/1/4/3", "title": "3. 天籁幻想" }
          ]
        },
        { "slug": "cn/216/1/5", "title": "鬼子来了" },
        { "slug": "cn/216/1/6", "title": "恋恋故乡情" },
        { "slug": "cn/216/1/7", "title": "返乡" },
        { "slug": "cn/216/1/8", "title": "湖南印象" },
        {
          "slug": "cn/216/1/9",
          "title": "上学记·乙",
          "child": [
            { "slug": "cn/216/1/9/1", "title": "1. 中央大学附中" },
            { "slug": "cn/216/1/9/2", "title": "2. 西方教科书" },
            { "slug": "cn/216/1/9/3", "title": "3. 逃离“修道院”" }
          ]
        }
      ]
    },
    {
      "slug": "cn/216/2",
      "title": "第二章（1939—1946）",
      "child": [
        {
          "slug": "cn/216/2/1",
          "title": "上学记·丙：迁徙的堡垒",
          "child": [
            { "slug": "cn/216/2/1/1", "title": "1. 自由散漫的作风" },
            { "slug": "cn/216/2/1/2", "title": "2. 三个大学从来都“联”得很好" },
            { "slug": "cn/216/2/1/3", "title": "3. 自由，学术之生命" },
            { "slug": "cn/216/2/1/4", "title": "4. 逃课、凑学分与窗外的聆听" },
            { "slug": "cn/216/2/1/5", "title": "5. 图书馆不是藏珍楼" },
            { "slug": "cn/216/2/1/6", "title": "6. 茶馆听吹牛，里根挂二牌" },
            { "slug": "cn/216/2/1/7", "title": "7. 兼职做教师" },
            { "slug": "cn/216/2/1/8", "title": "9. “天人交感”下的人生观转变" }
          ]
        },
        {
          "slug": "cn/216/2/2",
          "title": "几个难忘的人",
          "child": [
            { "slug": "cn/216/2/2/1", "title": "1. 一包热情的闻一多" },
            { "slug": "cn/216/2/2/2", "title": "2. 民主人士张奚若" },
            { "slug": "cn/216/2/2/3", "title": "3. 战国派雷海宗" },
            { "slug": "cn/216/2/2/4", "title": "4. 吴晗印象" },
            { "slug": "cn/216/2/2/5", "title": "5. 冯友兰先生" },
            { "slug": "cn/216/2/2/6", "title": "6. 金岳霖先生" },
            { "slug": "cn/216/2/2/7", "title": "7. 中国通温德，白俄噶邦福" },
            { "slug": "cn/216/2/2/8", "title": "8. 曾昭抡先生" },
            { "slug": "cn/216/2/2/9", "title": "9. 数学系" },
            { "slug": "cn/216/2/2/10", "title": "10. 物理系" }
          ]
        },
        { "slug": "cn/216/2/3", "title": "战火芬芳" },
        {
          "slug": "cn/216/2/4",
          "title": "“一二·一”运动",
          "child": [
            { "slug": "cn/216/2/4/1", "title": "1. “打倒孔祥熙！”" },
            { "slug": "cn/216/2/4/2", "title": "2. 一多先生被刺" },
            { "slug": "cn/216/2/4/3", "title": "3. 一个人的政治底线" }
          ]
        },
        { "slug": "cn/216/2/5", "title": "五柳读书记" },
        {
          "slug": "cn/216/2/6",
          "title": "忆同窗",
          "child": [
            { "slug": "cn/216/2/6/1", "title": "1. “科里红”何佶（吕荧）" },
            { "slug": "cn/216/2/6/2", "title": "2. 殷福生（殷海光）印象" },
            { "slug": "cn/216/2/6/3", "title": "3. 大才子王浩" },
            { "slug": "cn/216/2/6/4", "title": "4. 因言获罪的陈良璧" },
            { "slug": "cn/216/2/6/5", "title": "5．老友郑林生" }
          ]
        }
      ]
    },
    {
      "slug": "cn/216/3",
      "title": "第三章（1939—1950）",
      "child": [
        { "slug": "cn/216/3/1", "title": "教书台湾" },
        { "slug": "cn/216/3/2", "title": "日日江楼坐翠微" },
        { "slug": "cn/216/3/3", "title": "上学记·丁：革大学习" },
        { "slug": "cn/216/3/4", "title": "零敲碎打" }
      ]
    },
    { "slug": "cn/216/4", "title": "后记 把名字写在水上" },
    {
      "slug": "cn/216/5",
      "title": "成为中国那一代的知识分子",
      "child": [
        { "slug": "cn/216/5/1", "title": "一、亲历历史：那一代的人和事" },
        {
          "slug": "cn/216/5/2",
          "title": "二、幸福：什么是那一代中国的知识分子的追求？"
        },
        { "slug": "cn/216/5/3", "title": "三、风度与修养：现在还需要绅士吗？" },
        { "slug": "cn/216/5/4", "title": "结语" }
      ]
    }
  ]
}
