{"slug":"en/69","title":"Intimate Behaviour：A Zoologist's Classic Study of Human Intimacy","child":[{"slug":"en/69/1","title":"1 The Roots of Intimacy"},{"slug":"en/69/2","title":"2 Invitations to Sexual Intimacy"},{"slug":"en/69/3","title":"3 Sexual Intimacy"},{"slug":"en/69/4","title":"4 Social Intimacy"},{"slug":"en/69/5","title":"5 Specialized Intimacy"},{"slug":"en/69/6","title":"6 Substitutes for Intimacy"},{"slug":"en/69/7","title":"7 Object Intimacy"},{"slug":"en/69/8","title":"8 Self-Intimacy"},{"slug":"en/69/9","title":"9 Return to Intimacy"},{"slug":"en/69/10","title":"Chapter References"}]}