{"slug":"cn/193","title":"百年老狼：经济危机的脉络 - 马前卒(任冲昊)","child":[{"slug":"cn/193/1","title":"一 狼来了"},{"slug":"cn/193/2","title":"二 危机原理"},{"slug":"cn/193/3","title":"三 人算不如天算"},{"slug":"cn/193/4","title":"四 海盗本性"},{"slug":"cn/193/5","title":"五 技术的鞭子"},{"slug":"cn/193/6","title":"六 老本吃尽"},{"slug":"cn/193/7","title":"七 马克思还是凯恩斯"},{"slug":"cn/193/8","title":"八 经脉逆转"},{"slug":"cn/193/9","title":"九 老大难当"},{"slug":"cn/193/10","title":"十 自杀性攻击"},{"slug":"cn/193/11","title":"十一 记吃不记打"},{"slug":"cn/193/12","title":"十二 清算"}]}