{"slug":"yi/247","title":"汤姆叔叔的小屋 - 陈元飞译","child":[{"slug":"yi/247/1","title":"第一章 本章给读者介绍一位善良的人"},{"slug":"yi/247/2","title":"第二章 母亲"},{"slug":"yi/247/3","title":"第三章 既是丈夫，又是父亲"},{"slug":"yi/247/4","title":"第四章 汤姆叔叔的小屋之夜"},{"slug":"yi/247/5","title":"第五章 活财产易主时的感觉"},{"slug":"yi/247/6","title":"第六章 发觉"},{"slug":"yi/247/7","title":"第七章 母亲的奋争"},{"slug":"yi/247/8","title":"第八章 伊丽莎的逃亡之路"},{"slug":"yi/247/9","title":"第九章 从本章来看，参议员也是人"},{"slug":"yi/247/10","title":"第十章 财产起运"},{"slug":"yi/247/11","title":"第十一章 在本章中活财产有了非分之想"},{"slug":"yi/247/12","title":"第十二章 合法贸易选萃"},{"slug":"yi/247/13","title":"第十三章 公谊会村"},{"slug":"yi/247/14","title":"第十四章 伊万杰琳"},{"slug":"yi/247/15","title":"第十五章 汤姆的新主人及其他"},{"slug":"yi/247/16","title":"第十六章 汤姆的女主人及其见解"},{"slug":"yi/247/17","title":"第十七章 自由人的防卫"},{"slug":"yi/247/18","title":"第十八章 奥菲丽亚小姐的经历及其见解"},{"slug":"yi/247/19","title":"第十九章 奥菲丽亚小姐的经历及其见解续"},{"slug":"yi/247/20","title":"第二十章 托普西"},{"slug":"yi/247/21","title":"第二十一章 肯塔基"},{"slug":"yi/247/22","title":"第二十二章 草必枯干，花必凋谢"},{"slug":"yi/247/23","title":"第二十三章 亨利克"},{"slug":"yi/247/24","title":"第二十四章 预兆"},{"slug":"yi/247/25","title":"第二十五章 小福音使者"},{"slug":"yi/247/26","title":"第二十六章 死亡"},{"slug":"yi/247/27","title":"第二十七章 “这是世界末日”"},{"slug":"yi/247/28","title":"第二十八章 团圆"},{"slug":"yi/247/29","title":"第二十九章 不受保护的人们"},{"slug":"yi/247/30","title":"第三十章 黑奴货栈"},{"slug":"yi/247/31","title":"第三十一章 途中"},{"slug":"yi/247/32","title":"第三十二章 黑暗之处"},{"slug":"yi/247/33","title":"第三十三章 凯茜"},{"slug":"yi/247/34","title":"第三十四章 四分之一黑人血统姑娘的身世"},{"slug":"yi/247/35","title":"第三十五章 念物"},{"slug":"yi/247/36","title":"第三十六章 爱默琳和凯茜"},{"slug":"yi/247/37","title":"第三十七章 自由"},{"slug":"yi/247/38","title":"第三十八章 胜利"},{"slug":"yi/247/39","title":"第三十九章 计策"},{"slug":"yi/247/40","title":"第四十章 殉道者"},{"slug":"yi/247/41","title":"第四十一章 小主人"},{"slug":"yi/247/42","title":"第四十二章 一个可信的鬼故事"},{"slug":"yi/247/43","title":"第四十三章 收场"},{"slug":"yi/247/44","title":"第四十四章 解放者"},{"slug":"yi/247/45","title":"第四十五章 尾白"}]}