{"slug":"yi/175","title":"不公正的胜利 - 薛贵译","child":[{"slug":"yi/175/1","title":"第一章 美国的收入与税收"},{"slug":"yi/175/2","title":"第二章 从波士顿到里士满"},{"slug":"yi/175/3","title":"第三章 不公正如何获胜"},{"slug":"yi/175/4","title":"第四章 欢迎来到百慕兰"},{"slug":"yi/175/5","title":"第五章 税收不公正的螺旋上升"},{"slug":"yi/175/6","title":"第六章 如何阻止税收不公正的螺旋上升"},{"slug":"yi/175/7","title":"第七章 向富人征税"},{"slug":"yi/175/8","title":"第八章 超越拉弗"},{"slug":"yi/175/9","title":"第九章 充满可能性的世界"},{"slug":"yi/175/10","title":"结论 税收公正已刻不容缓"},{"slug":"yi/175/11","title":"致谢"}]}