{"slug":"cn/409","title":"禅海蠡测 - 南怀瑾","child":[{"slug":"cn/409/1","title":"禅宗之演变","child":[{"slug":"cn/409/1/1","title":"印度原来情形"},{"slug":"cn/409/1/2","title":"中国初期情形"},{"slug":"cn/409/1/3","title":"唐宋间之发展"},{"slug":"cn/409/1/4","title":"元明清之趋向"},{"slug":"cn/409/1/5","title":"与中国文化因缘"},{"slug":"cn/409/1/6","title":"对佛教之功绩"}]},{"slug":"cn/409/2","title":"禅宗之宗旨"},{"slug":"cn/409/3","title":"公案语录"},{"slug":"cn/409/4","title":"机锋转语"},{"slug":"cn/409/5","title":"证悟知解","child":[{"slug":"cn/409/5/1","title":"祖师禅与如来禅"},{"slug":"cn/409/5/2","title":"三关与顿渐"},{"slug":"cn/409/5/3","title":"闭关与打七"}]},{"slug":"cn/409/6","title":"宗师授受"},{"slug":"cn/409/7","title":"参话头"},{"slug":"cn/409/8","title":"神通妙用","child":[{"slug":"cn/409/8/1","title":"幻境相似神通之错误"},{"slug":"cn/409/8/2","title":"正定所发之通明"}]},{"slug":"cn/409/9","title":"生死之间"},{"slug":"cn/409/10","title":"中阴身略述","child":[{"slug":"cn/409/10/1","title":"三世因果——六道轮回——了生脱死之简说"},{"slug":"cn/409/10/2","title":"临命终时"},{"slug":"cn/409/10/3","title":"中阴身缘起"},{"slug":"cn/409/10/4","title":"生死决疑"},{"slug":"cn/409/10/5","title":"了生脱死"}]},{"slug":"cn/409/11","title":"醒与梦"},{"slug":"cn/409/12","title":"禅宗与教理","child":[{"slug":"cn/409/12/1","title":"由教入禅"},{"slug":"cn/409/12/2","title":"禅须通教"}]},{"slug":"cn/409/13","title":"禅宗与禅定","child":[{"slug":"cn/409/13/1","title":"禅定之学"},{"slug":"cn/409/13/2","title":"禅宗与禅定之间"}]},{"slug":"cn/409/14","title":"禅宗与净土","child":[{"slug":"cn/409/14/1","title":"净土究竟论"},{"slug":"cn/409/14/2","title":"禅宗究竟论"},{"slug":"cn/409/14/3","title":"禅净双修调和论"}]},{"slug":"cn/409/15","title":"禅宗与密宗","child":[{"slug":"cn/409/15/1","title":"西藏佛学渊源"},{"slug":"cn/409/15/2","title":"西藏佛法之崛起"},{"slug":"cn/409/15/3","title":"西藏后期佛法及派系"},{"slug":"cn/409/15/4","title":"西藏之显教"},{"slug":"cn/409/15/5","title":"西藏之密法"},{"slug":"cn/409/15/6","title":"藏密之特点"},{"slug":"cn/409/15/7","title":"显密优劣之商榷"}]},{"slug":"cn/409/16","title":"禅宗与丹道","child":[{"slug":"cn/409/16/1","title":"周秦时代之道家"},{"slug":"cn/409/16/2","title":"汉晋南北朝之道教"},{"slug":"cn/409/16/3","title":"唐宋元明清情形"},{"slug":"cn/409/16/4","title":"道教之经籍"},{"slug":"cn/409/16/5","title":"丹道之类别"},{"slug":"cn/409/16/6","title":"佛道优劣之辨"}]},{"slug":"cn/409/17","title":"禅宗与理学","child":[{"slug":"cn/409/17/1","title":"理学之先声"},{"slug":"cn/409/17/2","title":"北宋理学之崛起"},{"slug":"cn/409/17/3","title":"佛化儒家之踪迹"},{"slug":"cn/409/17/4","title":"禅宗与理学之渊源"},{"slug":"cn/409/17/5","title":"理学与禅宗之异同"},{"slug":"cn/409/17/6","title":"佛道儒化之教"}]},{"slug":"cn/409/18","title":"心物一元之佛法概论","child":[{"slug":"cn/409/18/1","title":"心法与力学"},{"slug":"cn/409/18/2","title":"心法与声音"},{"slug":"cn/409/18/3","title":"心法与光"},{"slug":"cn/409/18/4","title":"心法与电磁"},{"slug":"cn/409/18/5","title":"心理与生理"}]},{"slug":"cn/409/19","title":"佛法与西洋哲学","child":[{"slug":"cn/409/19/1","title":"希腊哲学初期心物之诤"},{"slug":"cn/409/19/2","title":"希腊盛时心物之诤"},{"slug":"cn/409/19/3","title":"希腊末期哲学"},{"slug":"cn/409/19/4","title":"希腊哲学合论"},{"slug":"cn/409/19/5","title":"欧洲中世纪哲学"},{"slug":"cn/409/19/6","title":"阿拉伯哲学"},{"slug":"cn/409/19/7","title":"近代哲学之变革及影响"},{"slug":"cn/409/19/8","title":"西洋哲学之批判"}]},{"slug":"cn/409/20","title":"修定与参禅法要","child":[{"slug":"cn/409/20/1","title":"初修禅定入门方法"},{"slug":"cn/409/20/2","title":"定慧影像"},{"slug":"cn/409/20/3","title":"参禅指月"}]},{"slug":"cn/409/21","title":"跋"},{"slug":"cn/409/22","title":"禅海蠡测剩语"}]}